materi_proto/__init__.py
materi_proto/py.typed
materi_proto/domains/__init__.py
materi_proto/domains/aria/__init__.py
materi_proto/domains/aria/v1_pb2.py
materi_proto/domains/aria/v1_pb2.pyi
materi_proto/domains/audit/__init__.py
materi_proto/domains/audit/v1_pb2.py
materi_proto/domains/audit/v1_pb2.pyi
materi_proto/domains/collaboration/__init__.py
materi_proto/domains/collaboration/v1_pb2.py
materi_proto/domains/collaboration/v1_pb2.pyi
materi_proto/domains/document/__init__.py
materi_proto/domains/document/v1_pb2.py
materi_proto/domains/document/v1_pb2.pyi
materi_proto/domains/envelope/__init__.py
materi_proto/domains/envelope/v1_pb2.py
materi_proto/domains/envelope/v1_pb2.pyi
materi_proto/domains/notification/__init__.py
materi_proto/domains/notification/v1_pb2.py
materi_proto/domains/notification/v1_pb2.pyi
materi_proto/domains/user/__init__.py
materi_proto/domains/user/v1_pb2.py
materi_proto/domains/user/v1_pb2.pyi
materi_proto/domains/workspace/__init__.py
materi_proto/domains/workspace/v1_pb2.py
materi_proto/domains/workspace/v1_pb2.pyi
materi_proto/shared/__init__.py
materi_proto/shared/v1_pb2.py
materi_proto/shared/v1_pb2.pyi
materi_proto-0.1.3.dist-info/METADATA
materi_proto-0.1.3.dist-info/WHEEL
materi_proto-0.1.3.dist-info/RECORD
