Metadata-Version: 2.4
Name: materi-proto
Version: 0.1.3
Summary: Materi Event Schema - Python bindings for Protocol Buffer event definitions
Project-URL: Homepage, https://github.com/materi/domain
Project-URL: Repository, https://github.com/materi/domain.git
Project-URL: Documentation, https://github.com/materi/domain/tree/main/manuscript/py#readme
Project-URL: Issues, https://github.com/materi/domain/issues
Author-email: Materi <engineering@materi.dev>
License-Expression: MIT
Keywords: events,grpc,materi,proto,protobuf,schema
Classifier: Development Status :: 4 - Beta
Classifier: Intended Audience :: Developers
Classifier: License :: OSI Approved :: MIT License
Classifier: Operating System :: OS Independent
Classifier: Programming Language :: Python :: 3
Classifier: Programming Language :: Python :: 3.11
Classifier: Programming Language :: Python :: 3.12
Classifier: Programming Language :: Python :: 3.13
Classifier: Typing :: Typed
Requires-Python: >=3.11
Requires-Dist: grpcio>=1.62.0
Requires-Dist: protobuf>=5.27.0
Provides-Extra: dev
Requires-Dist: grpcio-tools>=1.62.0; extra == 'dev'
Requires-Dist: mypy-protobuf>=3.6.0; extra == 'dev'
Requires-Dist: mypy>=1.10.0; extra == 'dev'
Requires-Dist: pytest-cov>=5.0.0; extra == 'dev'
Requires-Dist: pytest>=8.0.0; extra == 'dev'
Requires-Dist: ruff>=0.4.0; extra == 'dev'
